gharar/__init__.py
gharar/gharar.py
gharar-0.1.0.dist-info/AUTHORS.rst
gharar-0.1.0.dist-info/LICENSE
gharar-0.1.0.dist-info/METADATA
gharar-0.1.0.dist-info/WHEEL
gharar-0.1.0.dist-info/top_level.txt
gharar-0.1.0.dist-info/RECORD
