Metadata-Version: 2.1
Name: gharar
Version: 0.1.0
Summary: A modern, easy to use, feature-rich, and async ready API wrapper for Gharar written in Python.
Home-page: https://github.com/arastu/gharar
Author: Touhid Arastu
Author-email: touhid.arastu@gmail.com
License: MIT license
Keywords: gharar
Platform: UNKNOWN
Classifier: Development Status :: 2 - Pre-Alpha
Classifier: Intended Audience :: Developers
Classifier: License :: OSI Approved :: MIT License
Classifier: Natural Language :: English
Classifier: Programming Language :: Python :: 3
Classifier: Programming Language :: Python :: 3.5
Classifier: Programming Language :: Python :: 3.6
Classifier: Programming Language :: Python :: 3.7
Classifier: Programming Language :: Python :: 3.8
Requires-Python: >=3.5
